server.py
mseep_higress_ai_search_mcp_server-1.0.4.dist-info/METADATA
mseep_higress_ai_search_mcp_server-1.0.4.dist-info/WHEEL
mseep_higress_ai_search_mcp_server-1.0.4.dist-info/entry_points.txt
mseep_higress_ai_search_mcp_server-1.0.4.dist-info/top_level.txt
mseep_higress_ai_search_mcp_server-1.0.4.dist-info/RECORD
