Metadata-Version: 2.4
Name: mseep-higress-ai-search-mcp-server
Version: 1.0.4
Summary: Higress ai-search MCP Server
Author-email: mseep <support@skydeck.ai>
License:                                  Apache License
Requires-Python: >=3.10
Requires-Dist: fastmcp>=0.4.1
Requires-Dist: httpx>=0.24.0
Requires-Dist: tomli>=2.2.1
Requires-Dist: tomli-w>=1.2.0
